[
  {"q": "What PPE is required when working near conveyors?"},
  {"q": "How often should machine guards be inspected?"},
  {"q": "What is the lockout/tagout procedure steps?"},
  {"q": "How do you perform a risk assessment for a press machine?"},
  {"q": "Are there specific training requirements for forklift operators?"},
  {"q": "What are emergency stop requirements for conveyor systems?"},
  {"q": "When is a two-hand control required on stamping machines?"},
  {"q": "How to calculate guard distance for rotating shafts?"}
]
